setup.py
pyasteroids/GUI.py
pyasteroids/__main__.py
pyasteroids/arena.py
pyasteroids/asteroid.py
pyasteroids/collision_checker.py
pyasteroids/command_line.py
pyasteroids/mass.py
pyasteroids/model.py
pyasteroids/ship.py
pyasteroids.egg-info/PKG-INFO
pyasteroids.egg-info/SOURCES.txt
pyasteroids.egg-info/dependency_links.txt
pyasteroids.egg-info/entry_points.txt
pyasteroids.egg-info/requires.txt
pyasteroids.egg-info/top_level.txt