Metadata-Version: 1.0
Name: pyasteroids
Version: 0.5.2
Summary: Python asteroids game demonstrating pyagents library
Home-page: https://github.com/ggstuart/pyasteroids.git
Author: Graeme Stuart
Author-email: ggstuart@gmail.com
License: GPL
Keywords: agent based asteroids
Platform: UNKNOWN
Classifier: Development Status :: 3 - Alpha
Classifier: License :: OSI Approved :: GNU General Public License (GPL)
Classifier: Programming Language :: Python :: 2.7
Classifier: Topic :: Games/Entertainment :: Arcade
Classifier: Environment :: X11 Applications :: GTK
